<?xml version="1.0" encoding="utf-8"?>
<Dependencies>
  <ProductDependencies>
  </ProductDependencies>
  <ToolsetDependencies>
    <Dependency Name="Microsoft.DotNet.Arcade.Sdk" Version="6.0.0-beta.21425.4">
      <Uri>https://github.com/dotnet/arcade</Uri>
      <Sha>91c5da471db529ad34e052ad7b43ac9745b47ff7</Sha>
    </Dependency>
    <Dependency Name="Microsoft.DotNet.Helix.Sdk" Version="6.0.0-beta.21425.4">
      <Uri>https://github.com/dotnet/arcade</Uri>
      <Sha>91c5da471db529ad34e052ad7b43ac9745b47ff7</Sha>
    </Dependency>
  </ToolsetDependencies>
</Dependencies>
